igpicker/__init__.py
igpicker-0.4.4.dist-info/LICENSE
igpicker-0.4.4.dist-info/METADATA
igpicker-0.4.4.dist-info/WHEEL
igpicker-0.4.4.dist-info/top_level.txt
igpicker-0.4.4.dist-info/RECORD
