Metadata-Version: 2.1
Name: igpicker
Version: 0.4.4
Summary: WebScraping_Instagram
Home-page: https://github.com/kitchun0402/WebScraping_Instagram_igpicker
Author: Kenneth Hau
Author-email: kitchun0402@gmail.com
License: MIT
Platform: UNKNOWN
Requires-Python: >= 3
Requires-Dist: selenium (>=3.141.0)
Requires-Dist: bs4 (>=0.0.1)
Requires-Dist: ipython (>=7.8.0)
Requires-Dist: wget (>=3.2)
Requires-Dist: tqdm (>=4.36.1)
